telegram_bot/__init__.py
telegram_bot/bot.py
telegram_bot/buttons.py
telegram_bot/chataction.py
telegram_bot/chatmembers.py
telegram_bot/chatpermissions.py
telegram_bot/commands.py
telegram_bot/contact.py
telegram_bot/dice.py
telegram_bot/inputmedia.py
telegram_bot/location.py
telegram_bot/media.py
telegram_bot/messages.py
telegram_bot/misc.py
telegram_bot/polls.py
telegram_bot/response.py
telegram_bot/updates.py
b4t_python_telegram_bot-2.0.0.dist-info/LICENSE
b4t_python_telegram_bot-2.0.0.dist-info/METADATA
b4t_python_telegram_bot-2.0.0.dist-info/WHEEL
b4t_python_telegram_bot-2.0.0.dist-info/top_level.txt
b4t_python_telegram_bot-2.0.0.dist-info/RECORD
