Metadata-Version: 2.1
Name: b4t-python-telegram-bot
Version: 2.0.0
Summary: Simple and lightweight Telegram Bot
Home-page: https://github.com/brain4tech/b4t-python-telegram-bot
Author: Brain4Tech
Author-email: brain4techyt@gmail.com
License: MIT
Keywords: telegram,bot,api
Platform: UNKNOWN
Classifier: Development Status :: 5 - Production/Stable
Classifier: Intended Audience :: Developers
Classifier: Operating System :: OS Independent
Classifier: License :: OSI Approved :: MIT License
Classifier: Programming Language :: Python :: 3
License-File: LICENSE
Requires-Dist: requests
